hamming_digital_filters/__init__.py
hamming_digital_filters/gradient.py
hamming_digital_filters/lowpass.py
hamming_digital_filters-0.1.0.dist-info/METADATA
hamming_digital_filters-0.1.0.dist-info/WHEEL
hamming_digital_filters-0.1.0.dist-info/licenses/LICENSE
hamming_digital_filters-0.1.0.dist-info/RECORD
