Metadata-Version: 2.1
Name: hamming_digital_filters
Version: 0.1.0
Summary: Digital Filters by R.W.Hamming. Implementation.
Project-URL: Homepage, https://github.com/vbotka/hamming-digital-filters
Project-URL: Bug Tracker, https://github.com/vbotka/hamming-digital-filters/issues
Author-email: Vladimir Botka <vbotka@gmail.com>
License-File: LICENSE
Classifier: License :: OSI Approved :: BSD License
Classifier: Operating System :: OS Independent
Classifier: Programming Language :: Python :: 3
Requires-Python: >=3.7
